pywdpa/__init__.py
pywdpa/__main__.py
pywdpa/get_token.py
pywdpa/get_wdpa.py
pywdpa/pywdpa-runner.py
pywdpa/pywdpa.py
pywdpa-0.1.6.dist-info/LICENSE
pywdpa-0.1.6.dist-info/METADATA
pywdpa-0.1.6.dist-info/WHEEL
pywdpa-0.1.6.dist-info/entry_points.txt
pywdpa-0.1.6.dist-info/top_level.txt
pywdpa-0.1.6.dist-info/RECORD
