Metadata-Version: 2.1
Name: pywdpa
Version: 0.1.6
Summary: Easy access to world's protected areas
Home-page: https://ecology.ghislainv.fr/pywdpa
Author: Ghislain Vieilledent
Author-email: ghislain.vieilledent@cirad.fr
License: GPLv3
Project-URL: Documentation, https://ecology.ghislainv.fr/pywdpa
Project-URL: Source, https://github.com/ghislainv/pywdpa/
Project-URL: Traker, https://github.com/ghislainv/pywdpa/issues
Keywords: protected areas wdpa world database protected areas
Classifier: Development Status :: 4 - Beta
Classifier: License :: OSI Approved :: GNU General Public License v3 (GPLv3)
Classifier: Programming Language :: Python :: 3
Classifier: Operating System :: OS Independent
Classifier: Topic :: Scientific/Engineering :: Bio-Informatics
Requires-Python: >=3.6
License-File: LICENSE
Requires-Dist: numpy
Requires-Dist: gdal
Requires-Dist: requests
Provides-Extra: interactive
Requires-Dist: jupyter ; extra == 'interactive'
Requires-Dist: python-dotenv ; extra == 'interactive'
Requires-Dist: geopandas ; extra == 'interactive'
Requires-Dist: descartes ; extra == 'interactive'
Requires-Dist: folium ; extra == 'interactive'
